.gitignore
CHANGES.rst
MANIFEST.in
README.rst
README.txt
bootstrap.py
buildout.cfg
setup.py
collective/__init__.py
collective.emaillogin4.egg-info/PKG-INFO
collective.emaillogin4.egg-info/SOURCES.txt
collective.emaillogin4.egg-info/dependency_links.txt
collective.emaillogin4.egg-info/entry_points.txt
collective.emaillogin4.egg-info/namespace_packages.txt
collective.emaillogin4.egg-info/not-zip-safe
collective.emaillogin4.egg-info/requires.txt
collective.emaillogin4.egg-info/top_level.txt
collective/emaillogin4/__init__.py
collective/emaillogin4/configure.zcml
collective/emaillogin4/overrides.zcml
collective/emaillogin4/setuphandlers.py
collective/emaillogin4/tests.py
collective/emaillogin4/tests.txt
collective/emaillogin4/patches/__init__.py
collective/emaillogin4/patches/cmfplone/__init__.py
collective/emaillogin4/patches/cmfplone/utils.py
collective/emaillogin4/patches/pa_controlpanel/__init__.py
collective/emaillogin4/patches/pa_controlpanel/emaillogin.pt
collective/emaillogin4/patches/pa_controlpanel/overrides.zcml
collective/emaillogin4/patches/pa_controlpanel/security.py
collective/emaillogin4/patches/pa_controlpanel/tests/__init__.py
collective/emaillogin4/patches/pa_controlpanel/tests/security.txt
collective/emaillogin4/patches/pa_controlpanel/tests/test_doctests.py
collective/emaillogin4/patches/pa_upgrade/__init__.py
collective/emaillogin4/patches/pa_upgrade/final.py
collective/emaillogin4/patches/pa_upgrade/tests.py
collective/emaillogin4/patches/pa_users/__init__.py
collective/emaillogin4/patches/pa_users/interfaces.py
collective/emaillogin4/patches/pa_users/personalpreferences.py
collective/emaillogin4/patches/pa_users/register.py
collective/emaillogin4/patches/pa_users/utils.py
collective/emaillogin4/patches/pa_users/tests/__init__.py
collective/emaillogin4/patches/pa_users/tests/email_login.txt
collective/emaillogin4/patches/pa_users/tests/test_doctests.py
collective/emaillogin4/patches/pa_users/tests/test_userid_generator.py
collective/emaillogin4/patches/plonepas/__init__.py
collective/emaillogin4/patches/plonepas/property.py
collective/emaillogin4/profiles/default/collective.emaillogin4.txt
collective/emaillogin4/profiles/default/metadata.xml
collective/emaillogin4/profiles/default/propertiestool.xml
docs/INSTALL.txt
docs/LICENSE.GPL
docs/LICENSE.txt