Metadata-Version: 1.1
Name: collective.emaillogin4
Version: 1.3
Summary: Emaillogin fixes for Plone 4
Home-page: http://pypi.python.org/pypi/collective.emaillogin4
Author: Maurits van Rees
Author-email: m.van.rees@zestsoftware.nl
License: GPL
Platform: UNKNOWN
Classifier: Framework :: Plone
Classifier: Framework :: Plone :: 4.1
Classifier: Framework :: Plone :: 4.2
Classifier: Framework :: Plone :: 4.3
Classifier: Programming Language :: Python
